{"name":"Booke AI","slug":"booke-ai","tagline":"AI bookkeeper that works inside QuickBooks and Xero automatically","description":"Booke AI is an AI-powered bookkeeping assistant that works directly inside QuickBooks and Xero. Unlike other tools that just suggest actions, Booke AI actually clicks, categorizes, matches documents, and reconciles automatically within your existing accounting software. It handles transaction categorization, document matching, and reconciliation autonomously.","category":"Bookkeeping & Data Entry","url":"https://booke.ai","pricing":{"model":"freemium","startingPrice":"$20/mo"},"features":["Auto-categorization in QBO/Xero","Document matching","Automated reconciliation","Client communication portal","Error detection","Bank feed cleanup","Receipt matching","Multi-client management"],"pros":["Works directly inside existing software","Affordable pricing","Truly autonomous operation"],"cons":["Limited to QuickBooks and Xero","May need manual review for unusual transactions"],"rating":4.3,"lastUpdated":"2026-02-23","tags":["bookkeeping","quickbooks","xero","automation","categorization"]}
